mezo_agent/__init__.py
mezo_agent/characters.py
mezo_agent/chat.py
mezo_agent/config.py
mezo_agent/parsing.py
mezo_agent/safe_mode_btc_tool.py
mezo_agent/swap_musd_btc.py
mezo_agent/token_balance_tool.py
mezo_agent/token_price_tool.py
mezo_agent/token_utils.py
mezo_agent/transaction.py
mezo_agent/twitter_client.py
mezo_agent/twitter_manager.py
mezo_agent/utils.py
mezo_agent/data/new_router.json
mezoAgent-0.8.5.dist-info/METADATA
mezoAgent-0.8.5.dist-info/WHEEL
mezoAgent-0.8.5.dist-info/top_level.txt
mezoAgent-0.8.5.dist-info/RECORD
